felyx/__init__.py
felyx/__main__.py
felyx/about.py
felyx/app.py
felyx/assets/handle.png
felyx/assets/minus1.png
felyx/assets/minus10.png
felyx/assets/minus5.png
felyx/assets/plus.png
felyx/assets/plus1.png
felyx/assets/plus10.png
felyx/assets/plus5.png
felyx/assets/style.qss
felyx/assets.py
felyx/coders.py
felyx/command.py
felyx/config/config.yml
felyx/config.py
felyx/constants.py
felyx/cursor.py
felyx/data.py
felyx/event.py
felyx/exceptions.py
felyx/files.py
felyx/format.py
felyx/images.py
felyx/mainwindow.py
felyx/menu.py
felyx/message.py
felyx/occurrence.py
felyx/textedit.py
felyx/timeline.py
felyx/timepane.py
felyx/timescale.py
felyx/utils.py
felyx/video.py
felyx-0.12.17.dist-info/entry_points.txt
felyx-0.12.17.dist-info/WHEEL
felyx-0.12.17.dist-info/METADATA
felyx-0.12.17.dist-info/licenses/LICENSE
felyx-0.12.17.dist-info/RECORD
