Metadata-Version: 2.1
Name: felyx
Version: 0.12.17
Summary: Video coder for psychological experiments
License: GPL-3.0-or-later
Author-email: Rafael Laboissière <rafael.laboissiere@cnrs.fr>,Esteban Milleret <esteban.milleret@etu.univ-grenoble-alpes.fr>
Requires-Python: >=3.8
Requires-Dist: PySide6>=6.9.0
Requires-Dist: appdirs>=1.4.4
Requires-Dist: colour>=0.1.5
Requires-Dist: docopt-ng>=0.6.2
Requires-Dist: numpy>=2.2.5
Requires-Dist: pandas>=2.2.2
Requires-Dist: pyyaml>=6.0.1
